README.rst
setup.py
grpc_interceptor_headers/__init__.py
grpc_interceptor_headers/generic_client_interceptor.py
grpc_interceptor_headers/header_manipulator_client_interceptor.py
grpc_interceptor_headers/request_header_validator_interceptor.py
grpc_interceptor_headers.egg-info/PKG-INFO
grpc_interceptor_headers.egg-info/SOURCES.txt
grpc_interceptor_headers.egg-info/dependency_links.txt
grpc_interceptor_headers.egg-info/top_level.txt
samples/__init__.py
samples/greeter_client.py
samples/greeter_server.py
samples/helloworld_pb2.py
samples/helloworld_pb2_grpc.py