Metadata-Version: 1.1
Name: grpc-interceptor-headers
Version: 0.1.0
Summary: grpc_interceptor_headers, copied from grpc official repo
Home-page: https://github.com/sempr/grpc-interceptor-headers
Author: Sempr Wang
Author-email: iamsempr@gmail.com
License: MIT
Platform: UNKNOWN
Classifier: Development Status :: 2 - Pre-Alpha
Classifier: License :: OSI Approved :: MIT License
Classifier: Programming Language :: Python
Classifier: Programming Language :: Python :: 2
Classifier: Programming Language :: Python :: 2.7
Classifier: Programming Language :: Python :: 3
Classifier: Programming Language :: Python :: 3.4
Classifier: Programming Language :: Python :: 3.5
Classifier: Programming Language :: Python :: 3.6
Classifier: Programming Language :: Python :: 3.7
